AliYunyunXiaoZhuliQiye10BeiXiaonengTishengAnliJiFix1/README.md
AliYunyunXiaoZhuliQiye10BeiXiaonengTishengAnliJiFix1/__init__.py
AliYunyunXiaoZhuliQiye10BeiXiaonengTishengAnliJiFix1/__main__.py
AliYunyunXiaoZhuliQiye10BeiXiaonengTishengAnliJiFix1/file.pdf
AliYunyunXiaoZhuliQiye10BeiXiaonengTishengAnliJiFix1/index.html
ali_yunyun_xiao_zhuli_qiye_10_bei_xiaoneng_tisheng_anli_ji_fix1-2025.3.25.1.dist-info/METADATA
ali_yunyun_xiao_zhuli_qiye_10_bei_xiaoneng_tisheng_anli_ji_fix1-2025.3.25.1.dist-info/WHEEL
ali_yunyun_xiao_zhuli_qiye_10_bei_xiaoneng_tisheng_anli_ji_fix1-2025.3.25.1.dist-info/entry_points.txt
ali_yunyun_xiao_zhuli_qiye_10_bei_xiaoneng_tisheng_anli_ji_fix1-2025.3.25.1.dist-info/top_level.txt
ali_yunyun_xiao_zhuli_qiye_10_bei_xiaoneng_tisheng_anli_ji_fix1-2025.3.25.1.dist-info/RECORD
